imshowpair.py
imshowpair-0.1.0.dist-info/AUTHORS.rst
imshowpair-0.1.0.dist-info/LICENSE.rst
imshowpair-0.1.0.dist-info/METADATA
imshowpair-0.1.0.dist-info/WHEEL
imshowpair-0.1.0.dist-info/top_level.txt
imshowpair-0.1.0.dist-info/RECORD
