Metadata-Version: 2.1
Name: imshowpair
Version: 0.1.0
Summary: Compare two images
Home-page: https://github.com/lebedov/imshowpair
Author: Lev E. Givon
Author-email: lev@columbia.edu
License: BSD
Platform: UNKNOWN
Classifier: Development Status :: 3 - Alpha
Classifier: Intended Audience :: Developers
Classifier: Intended Audience :: Science/Research
Classifier: License :: OSI Approved :: BSD License
Classifier: Operating System :: OS Independent
Classifier: Programming Language :: Python
Classifier: Programming Language :: Python :: 2.7
Classifier: Programming Language :: Python :: 3
Classifier: Programming Language :: Python :: 3.4
Classifier: Programming Language :: Python :: 3.5
Classifier: Programming Language :: Python :: 3.6
Classifier: Programming Language :: Python :: 3.7
Classifier: Topic :: Scientific/Engineering
Classifier: Topic :: Software Development
Requires-Dist: matplotlib (>=2.0.0)
Provides-Extra: extra_funcs
Requires-Dist: scikit-image (>=0.14) ; extra == 'extra_funcs'
